{"cameraMode":{"drawMode":0,"name":"Shaded","section":"Shading Mode"},"sceneLighting":true,"audioPlay":false,"sceneViewState":{"showFog":true,"showMaterialUpdate":false,"showSkybox":true,"showFlares":true,"showImageEffects":true,"showParticleSystems":true},"in2DMode":false,"pivot":{"x":-1.184816837310791,"y":1.834585189819336,"z":0.8177356719970703},"rotation":{"x":0.02442210726439953,"y":-0.9754055142402649,"z":0.16392265260219575,"w":0.145321786403656},"size":26.122100830078126,"orthographic":false}